noun_phrase_ua/__init__.py
noun_phrase_ua/nlp.py
noun_phrase_ua/ukrainian-iu-ud-2.3-181115.udpipe
noun_phrase_ua/universal_dependency_model.py
noun_phrase_ua/gazetteers/gazetteer.csv
noun_phrase_ua-0.0.5.dist-info/LICENSE
noun_phrase_ua-0.0.5.dist-info/METADATA
noun_phrase_ua-0.0.5.dist-info/WHEEL
noun_phrase_ua-0.0.5.dist-info/top_level.txt
noun_phrase_ua-0.0.5.dist-info/RECORD
