Metadata-Version: 2.1
Name: noun-phrase-ua
Version: 0.0.5
Summary: Noun phrase extractor for the Ukrainian language
Home-page: https://github.com/artemkramov/np-extractor-ua
Author: Artem Kramov
Author-email: artemkramov@gmail.com
License: UNKNOWN
Platform: UNKNOWN
Requires-Dist: ufal.udpipe
Requires-Dist: dateparser
